cs/logutils.py
cs_logutils-20250323.dist-info/WHEEL
cs_logutils-20250323.dist-info/METADATA
cs_logutils-20250323.dist-info/RECORD
