Metadata-Version: 2.4
Name: cs-logutils
Version: 20250323
Summary: Logging convenience routines.
Keywords: python2,python3
Author-email: Cameron Simpson <cs@cskk.id.au>
Classifier: Programming Language :: Python
Classifier: Programming Language :: Python :: 2
Classifier: Programming Language :: Python :: 3
Classifier: Development Status :: 4 - Beta
Classifier: Intended Audience :: Developers
Classifier: Operating System :: OS Independent
Classifier: Topic :: Software Development :: Libraries :: Python Modules
Classifier: License :: OSI Approved :: GNU General Public License v3 or later (GPLv3+)
Requires-Dist: cs.ansi_colour>=20200729
Requires-Dist: cs.context>=20210306
Requires-Dist: cs.deco>=20250306
Requires-Dist: cs.lex>=20250103
Requires-Dist: cs.pfx>=20250308
Requires-Dist: cs.py.func>=20240630
Project-URL: MonoRepo Commits, https://bitbucket.org/cameron_simpson/css/commits/branch/main
Project-URL: Monorepo Git Mirror, https://github.com/cameron-simpson/css
Project-URL: Monorepo Hg/Mercurial Mirror, https://hg.sr.ht/~cameron-simpson/css
Project-URL: Source, https://github.com/cameron-simpson/css/blob/main/lib/python/cs/logutils.py
